{"paths": {"admin/js/vendor/select2/i18n/ru.js": "admin/js/vendor/select2/i18n/ru.934aa95f5b5f.js", "admin/js/vendor/select2/i18n/fa.js": "admin/js/vendor/select2/i18n/fa.3b5bd1961cfd.js", "admin/js/vendor/select2/i18n/zh-CN.js": "admin/js/vendor/select2/i18n/zh-CN.2cff662ec5f9.js", "admin/js/vendor/select2/i18n/af.js": "admin/js/vendor/select2/i18n/af.4f6fcd73488c.js", "admin/js/vendor/select2/i18n/sv.js": "admin/js/vendor/select2/i18n/sv.7a9c2f71e777.js", "admin/js/vendor/select2/i18n/cs.js": "admin/js/vendor/select2/i18n/cs.4f43e8e7d33a.js", "admin/js/vendor/select2/i18n/pt.js": "admin/js/vendor/select2/i18n/pt.33b4a3b44d43.js", "admin/js/vendor/select2/i18n/tk.js": "admin/js/vendor/select2/i18n/tk.7c572a68c78f.js", "admin/js/vendor/select2/i18n/dsb.js": "admin/js/vendor/select2/i18n/dsb.56372c92d2f1.js", "admin/js/vendor/select2/i18n/es.js": "admin/js/vendor/select2/i18n/es.66dbc2652fb1.js", "admin/js/vendor/select2/i18n/he.js": "admin/js/vendor/select2/i18n/he.e420ff6cd3ed.js", "admin/js/vendor/select2/i18n/hy.js": "admin/js/vendor/select2/i18n/hy.c7babaeef5a6.js", "admin/js/vendor/select2/i18n/it.js": "admin/js/vendor/select2/i18n/it.be4fe8d365b5.js", "admin/js/vendor/select2/i18n/pt-BR.js": "admin/js/vendor/select2/i18n/pt-BR.e1b294433e7f.js", "admin/js/vendor/select2/i18n/en.js": "admin/js/vendor/select2/i18n/en.cf932ba09a98.js", "admin/js/vendor/select2/i18n/id.js": "admin/js/vendor/select2/i18n/id.04debded514d.js", "admin/js/vendor/select2/i18n/ms.js": "admin/js/vendor/select2/i18n/ms.4ba82c9a51ce.js", "admin/js/vendor/select2/i18n/hi.js": "admin/js/vendor/select2/i18n/hi.70640d41628f.js", "admin/js/vendor/select2/i18n/eu.js": "admin/js/vendor/select2/i18n/eu.adfe5c97b72c.js", "admin/js/vendor/select2/i18n/sk.js": "admin/js/vendor/select2/i18n/sk.33d02cef8d11.js", "admin/js/vendor/select2/i18n/zh-TW.js": "admin/js/vendor/select2/i18n/zh-TW.04554a227c2b.js", "admin/js/vendor/select2/i18n/el.js": "admin/js/vendor/select2/i18n/el.27097f071856.js", "admin/js/vendor/select2/i18n/ro.js": "admin/js/vendor/select2/i18n/ro.f75cb460ec3b.js", "admin/js/vendor/select2/i18n/uk.js": "admin/js/vendor/select2/i18n/uk.8cede7f4803c.js", "admin/js/vendor/select2/i18n/gl.js": "admin/js/vendor/select2/i18n/gl.d99b1fedaa86.js", "admin/js/vendor/select2/i18n/sl.js": "admin/js/vendor/select2/i18n/sl.131a78bc0752.js", "admin/js/vendor/select2/i18n/is.js": "admin/js/vendor/select2/i18n/is.3ddd9a6a97e9.js", "admin/js/vendor/select2/i18n/ps.js": "admin/js/vendor/select2/i18n/ps.38dfa47af9e0.js", "admin/js/vendor/select2/i18n/bg.js": "admin/js/vendor/select2/i18n/bg.39b8be30d4f0.js", "admin/js/vendor/select2/i18n/fi.js": "admin/js/vendor/select2/i18n/fi.614ec42aa9ba.js", "admin/js/vendor/select2/i18n/pl.js": "admin/js/vendor/select2/i18n/pl.6031b4f16452.js", "admin/js/vendor/select2/i18n/ca.js": "admin/js/vendor/select2/i18n/ca.a166b745933a.js", "admin/js/vendor/select2/i18n/bs.js": "admin/js/vendor/select2/i18n/bs.91624382358e.js", "admin/js/vendor/select2/i18n/lv.js": "admin/js/vendor/select2/i18n/lv.08e62128eac1.js", "admin/js/vendor/select2/i18n/ar.js": "admin/js/vendor/select2/i18n/ar.65aa8e36bf5d.js", "admin/js/vendor/select2/i18n/hr.js": "admin/js/vendor/select2/i18n/hr.a2b092cc1147.js", "admin/js/vendor/select2/i18n/ja.js": "admin/js/vendor/select2/i18n/ja.170ae885d74f.js", "admin/js/vendor/select2/i18n/tr.js": "admin/js/vendor/select2/i18n/tr.b5a0643d1545.js", "admin/js/vendor/select2/i18n/fr.js": "admin/js/vendor/select2/i18n/fr.05e0542fcfe6.js", "admin/js/vendor/select2/i18n/sr-Cyrl.js": "admin/js/vendor/select2/i18n/sr-Cyrl.f254bb8c4c7c.js", "admin/js/vendor/select2/i18n/vi.js": "admin/js/vendor/select2/i18n/vi.097a5b75b3e1.js", "admin/js/vendor/select2/i18n/nb.js": "admin/js/vendor/select2/i18n/nb.da2fce143f27.js", "admin/js/vendor/select2/i18n/ne.js": "admin/js/vendor/select2/i18n/ne.3d79fd3f08db.js", "admin/js/vendor/select2/i18n/de.js": "admin/js/vendor/select2/i18n/de.8a1c222b0204.js", "admin/js/vendor/select2/i18n/ko.js": "admin/js/vendor/select2/i18n/ko.e7be6c20e673.js", "admin/js/vendor/select2/i18n/ka.js": "admin/js/vendor/select2/i18n/ka.2083264a54f0.js", "admin/js/vendor/select2/i18n/sr.js": "admin/js/vendor/select2/i18n/sr.5ed85a48f483.js", "admin/js/vendor/select2/i18n/hu.js": "admin/js/vendor/select2/i18n/hu.6ec6039cb8a3.js", "admin/js/vendor/select2/i18n/lt.js": "admin/js/vendor/select2/i18n/lt.23c7ce903300.js", "admin/js/vendor/select2/i18n/nl.js": "admin/js/vendor/select2/i18n/nl.997868a37ed8.js", "admin/js/vendor/select2/i18n/km.js": "admin/js/vendor/select2/i18n/km.c23089cb06ca.js", "admin/js/vendor/select2/i18n/hsb.js": "admin/js/vendor/select2/i18n/hsb.fa3b55265efe.js", "admin/js/vendor/select2/i18n/sq.js": "admin/js/vendor/select2/i18n/sq.5636b60d29c9.js", "admin/js/vendor/select2/i18n/mk.js": "admin/js/vendor/select2/i18n/mk.dabbb9087130.js", "admin/js/vendor/select2/i18n/et.js": "admin/js/vendor/select2/i18n/et.2b96fd98289d.js", "admin/js/vendor/select2/i18n/da.js": "admin/js/vendor/select2/i18n/da.766346afe4dd.js", "admin/js/vendor/select2/i18n/th.js": "admin/js/vendor/select2/i18n/th.f38c20b0221b.js", "admin/js/vendor/select2/i18n/az.js": "admin/js/vendor/select2/i18n/az.270c257daf81.js", "admin/js/vendor/select2/i18n/bn.js": "admin/js/vendor/select2/i18n/bn.6d42b4dd5665.js", "admin_tools/css/jquery/images/ui-bg_glass_75_e6e6e6_1x400.png": "admin_tools/css/jquery/images/ui-bg_glass_75_e6e6e6_1x400.f4359b555324.png", "admin_tools/css/jquery/images/ui-bg_highlight-soft_75_cccccc_1x100.png": "admin_tools/css/jquery/images/ui-bg_highlight-soft_75_cccccc_1x100.3522b9340f17.png", "admin_tools/css/jquery/images/ui-bg_flat_75_ffffff_40x100.png": "admin_tools/css/jquery/images/ui-bg_flat_75_ffffff_40x100.a6eee1769b1f.png", "admin_tools/css/jquery/images/ui-bg_glass_75_dadada_1x400.png": "admin_tools/css/jquery/images/ui-bg_glass_75_dadada_1x400.46db09269ae3.png", "admin_tools/css/jquery/images/ui-bg_glass_65_ffffff_1x400.png": "admin_tools/css/jquery/images/ui-bg_glass_65_ffffff_1x400.3dec487cc3fe.png", "admin_tools/css/jquery/images/ui-bg_glass_95_fef1ec_1x400.png": "admin_tools/css/jquery/images/ui-bg_glass_95_fef1ec_1x400.4011a0e9203e.png", "admin_tools/css/jquery/images/animated-overlay.gif": "admin_tools/css/jquery/images/animated-overlay.2b912f7c0653.gif", "admin_tools/css/jquery/images/ui-bg_flat_0_aaaaaa_40x100.png": "admin_tools/css/jquery/images/ui-bg_flat_0_aaaaaa_40x100.3f4936bf71c0.png", "admin_tools/css/jquery/images/ui-bg_glass_55_fbf9ee_1x400.png": "admin_tools/css/jquery/images/ui-bg_glass_55_fbf9ee_1x400.0965a6a8e978.png", "admin_tools/css/jquery/images/ui-icons_222222_256x240.png": "admin_tools/css/jquery/images/ui-icons_222222_256x240.a1b3887a86cf.png", "admin_tools/css/jquery/images/ui-icons_cd0a0a_256x240.png": "admin_tools/css/jquery/images/ui-icons_cd0a0a_256x240.5c78585b80fb.png", "admin_tools/css/jquery/images/ui-icons_454545_256x240.png": "admin_tools/css/jquery/images/ui-icons_454545_256x240.6b29e362591a.png", "admin_tools/css/jquery/images/ui-icons_888888_256x240.png": "admin_tools/css/jquery/images/ui-icons_888888_256x240.302ae7a7aed5.png", "admin_tools/css/jquery/images/ui-icons_2e83ff_256x240.png": "admin_tools/css/jquery/images/ui-icons_2e83ff_256x240.764c37efbf6d.png", "admin/js/vendor/select2/select2.full.js": "admin/js/vendor/select2/select2.full.c2afdeda3058.js", "admin/js/vendor/select2/LICENSE.md": "admin/js/vendor/select2/LICENSE.f94142512c91.md", "admin/js/vendor/select2/select2.full.min.js": "admin/js/vendor/select2/select2.full.min.fcd7500d8e13.js", "admin/js/vendor/jquery/jquery.min.js": "admin/js/vendor/jquery/jquery.min.dc5e7f18c8d3.js", "admin/js/vendor/jquery/LICENSE.txt": "admin/js/vendor/jquery/LICENSE.75308107741f.txt", "admin/js/vendor/jquery/jquery.js": "admin/js/vendor/jquery/jquery.23c7c5d2d131.js", "admin/js/vendor/xregexp/LICENSE.txt": "admin/js/vendor/xregexp/LICENSE.bf79e414957a.txt", "admin/js/vendor/xregexp/xregexp.min.js": "admin/js/vendor/xregexp/xregexp.min.b0439563a5d3.js", "admin/js/vendor/xregexp/xregexp.js": "admin/js/vendor/xregexp/xregexp.efda034b9537.js", "admin/css/vendor/select2/select2.css": "admin/css/vendor/select2/select2.a2194c262648.css", "admin/css/vendor/select2/select2.min.css": "admin/css/vendor/select2/select2.min.9f54e6414f87.css", "admin/css/vendor/select2/LICENSE-SELECT2.md": "admin/css/vendor/select2/LICENSE-SELECT2.f94142512c91.md", "admin_tools/js/jquery/jquery.min.js": "admin_tools/js/jquery/jquery.min.dc5e7f18c8d3.js", "admin_tools/js/jquery/jquery-ui.min.js": "admin_tools/js/jquery/jquery-ui.min.0a497d4661df.js", "admin_tools/js/jquery/jquery.cookie.min.js": "admin_tools/js/jquery/jquery.cookie.min.67afdc8bb995.js", "admin_tools/js/jquery/jquery.dashboard.js": "admin_tools/js/jquery/jquery.dashboard.f86e627a3f09.js", "admin_tools/css/jquery/jquery-ui.css": "admin_tools/css/jquery/jquery-ui.16ff42e7ce74.css", "admin/js/admin/DateTimeShortcuts.js": "admin/js/admin/DateTimeShortcuts.5548f99471bf.js", "admin/js/admin/RelatedObjectLookups.js": "admin/js/admin/RelatedObjectLookups.b4d76b6aaf0b.js", "admin/img/gis/move_vertex_on.svg": "admin/img/gis/move_vertex_on.0047eba25b67.svg", "admin/img/gis/move_vertex_off.svg": "admin/img/gis/move_vertex_off.7a23bf31ef8a.svg", "learn/js/main.js": "learn/js/main.e5180672acea.js", "admin_tools/js/utils.js": "admin_tools/js/utils.3aad97e778f5.js", "admin_tools/js/json.min.js": "admin_tools/js/json.min.4b76179bb212.js", "admin_tools/images/admin-tools.png": "admin_tools/images/admin-tools.f1dc96e7b4ff.png", "admin_tools/images/django.png": "admin_tools/images/django.6bfe5c7438d6.png", "admin_tools/css/theming.css": "admin_tools/css/theming.fe53bd7686c8.css", "admin_tools/js/menu.js": "admin_tools/js/menu.583d6ac2c509.js", "admin_tools/css/menu.css": "admin_tools/css/menu.f3fed43132cd.css", "admin_tools/css/menu-ie.css": "admin_tools/css/menu-ie.55e1b558d1b2.css", "admin_tools/js/dashboard.js": "admin_tools/js/dashboard.9e3fe750a7b4.js", "admin_tools/css/dashboard-ie.css": "admin_tools/css/dashboard-ie.c9ddba1fa336.css", "admin_tools/css/dashboard.css": "admin_tools/css/dashboard.97f126cfcc19.css", "admin/js/core.js": "admin/js/core.ccd84108ec57.js", "admin/js/collapse.js": "admin/js/collapse.f84e7410290f.js", "admin/js/inlines.js": "admin/js/inlines.7596b7fd289e.js", "admin/js/popup_response.js": "admin/js/popup_response.c6cc78ea5551.js", "admin/js/cancel.js": "admin/js/cancel.ecc4c5ca7b32.js", "admin/js/prepopulate_init.js": "admin/js/prepopulate_init.e056047b7a7e.js", "admin/js/change_form.js": "admin/js/change_form.9d8ca4f96b75.js", "admin/js/SelectFilter2.js": "admin/js/SelectFilter2.d250dcb52a9a.js", "admin/js/SelectBox.js": "admin/js/SelectBox.8161741c7647.js", "admin/js/urlify.js": "admin/js/urlify.25cc3eac8123.js", "admin/js/prepopulate.js": "admin/js/prepopulate.bd2361dfd64d.js", "admin/js/autocomplete.js": "admin/js/autocomplete.b6b77d0e5906.js", "admin/js/calendar.js": "admin/js/calendar.f8a5d055eb33.js", "admin/js/nav_sidebar.js": "admin/js/nav_sidebar.7605597ddf52.js", "admin/js/actions.js": "admin/js/actions.a6d23e8853fd.js", "admin/js/jquery.init.js": "admin/js/jquery.init.b7781a0897fc.js", "admin/fonts/Roboto-Regular-webfont.woff": "admin/fonts/Roboto-Regular-webfont.35b07eb2f871.woff", "admin/fonts/Roboto-Bold-webfont.woff": "admin/fonts/Roboto-Bold-webfont.50d75e48e0a3.woff", "admin/fonts/LICENSE.txt": "admin/fonts/LICENSE.d273d63619c9.txt", "admin/fonts/Roboto-Light-webfont.woff": "admin/fonts/Roboto-Light-webfont.c73eb1ceba33.woff", "admin/fonts/README.txt": "admin/fonts/README.ab99e6b541ea.txt", "admin/css/responsive.css": "admin/css/responsive.b128bdf0edef.css", "admin/css/base.css": "admin/css/base.1f418065fc2c.css", "admin/css/autocomplete.css": "admin/css/autocomplete.4a81fc4242d0.css", "admin/css/widgets.css": "admin/css/widgets.694d845b2cb1.css", "admin/css/responsive_rtl.css": "admin/css/responsive_rtl.e13ae754cceb.css", "admin/css/nav_sidebar.css": "admin/css/nav_sidebar.0fd434145f4d.css", "admin/css/login.css": "admin/css/login.c35adf41bb6e.css", "admin/css/rtl.css": "admin/css/rtl.4bc23eb90919.css", "admin/css/dashboard.css": "admin/css/dashboard.be83f13e4369.css", "admin/css/forms.css": "admin/css/forms.1d89ec6432f5.css", "admin/css/changelists.css": "admin/css/changelists.c70d77c47e69.css", "admin/css/fonts.css": "admin/css/fonts.168bab448fee.css", "admin/img/icon-changelink.svg": "admin/img/icon-changelink.18d2fd706348.svg", "admin/img/icon-yes.svg": "admin/img/icon-yes.d2f9f035226a.svg", "admin/img/sorting-icons.svg": "admin/img/sorting-icons.3a097b59f104.svg", "admin/img/selector-icons.svg": "admin/img/selector-icons.b4555096cea2.svg", "admin/img/icon-no.svg": "admin/img/icon-no.439e821418cd.svg", "admin/img/inline-delete.svg": "admin/img/inline-delete.fec1b761f254.svg", "admin/img/icon-clock.svg": "admin/img/icon-clock.e1d4dfac3f2b.svg", "admin/img/icon-unknown-alt.svg": "admin/img/icon-unknown-alt.81536e128bb6.svg", "admin/img/search.svg": "admin/img/search.7cf54ff789c6.svg", "admin/img/icon-viewlink.svg": "admin/img/icon-viewlink.41eb31f7826e.svg", "admin/img/tooltag-arrowright.svg": "admin/img/tooltag-arrowright.bbfb788a849e.svg", "admin/img/icon-addlink.svg": "admin/img/icon-addlink.d519b3bab011.svg", "admin/img/tooltag-add.svg": "admin/img/tooltag-add.e59d620a9742.svg", "admin/img/icon-alert.svg": "admin/img/icon-alert.034cc7d8a67f.svg", "admin/img/icon-deletelink.svg": "admin/img/icon-deletelink.564ef9dc3854.svg", "admin/img/icon-unknown.svg": "admin/img/icon-unknown.a18cb4398978.svg", "admin/img/icon-calendar.svg": "admin/img/icon-calendar.ac7aea671bea.svg", "admin/img/LICENSE": "admin/img/LICENSE.2c54f4e1ca1c", "admin/img/calendar-icons.svg": "admin/img/calendar-icons.39b290681a8b.svg", "admin/img/README.txt": "admin/img/README.a70711a38d87.txt", "js/bootstrap.min.js": "js/bootstrap.min.2abd6b85cc11.js", "js/bootstrap.min.js.map": "js/bootstrap.min.js.f72523ed2e46.map", "js/bootstrap.bundle.min.js": "js/bootstrap.bundle.min.1fa88fa805d9.js", "js/bootstrap.bundle.min.js.map": "js/bootstrap.bundle.min.js.0ed0cd26b049.map", "_assets/fig_inserir_usuario.gif": "_assets/fig_inserir_usuario.8bc12eb1acd5.gif", "_assets/fig_login_acesso.gif": "_assets/fig_login_acesso.0b5b9c336d94.gif", "_assets/fig_lista_produtos.gif": "_assets/fig_lista_produtos.99ee7a8e7bd7.gif", "_assets/fig_pesquisa_produtos.gif": "_assets/fig_pesquisa_produtos.b75e63130947.gif", "_assets/text_bnwcoffee.gif": "_assets/text_bnwcoffee.4ec41f080031.gif", "_assets/logo_andes.gif": "_assets/logo_andes.836a46dd900b.gif", "_assets/botao_search.png": "_assets/botao_search.8e02355e8e5a.png", "_assets/fig_produtos.gif": "_assets/fig_produtos.f1a58a1a29fe.gif", "_assets/fig_botao_login.gif": "_assets/fig_botao_login.a42eed03eebe.gif", "_assets/fig_franquias_listagem.gif": "_assets/fig_franquias_listagem.bc97cc86183e.gif", "_css/produto_detalhe.css": "_css/produto_detalhe.e98b0578ddff.css", "_css/crudNEW.css": "_css/crudNEW.f299f1f601e1.css", "_css/alteracao.css": "_css/alteracao.e58209beaeab.css", "_css/produtos.css": "_css/produtos.19c4e1a56ed6.css", "_css/pedidos.css": "_css/pedidos.c663985f5b79.css", "_css/menu.css": "_css/menu.301b077fc506.css", "_css/inclusao.css": "_css/inclusao.519aa40b8825.css", "_css/contato.css": "_css/contato.1d1a55ef9eb4.css", "_css/menu_ini.css": "_css/menu_ini.47282c3b6411.css", "_css/login.css": "_css/login.b1c41d9af594.css", "_css/listarPedidos.css": "_css/listarPedidos.3728f55486da.css", "_css/novo-transportadora.css": "_css/novo-transportadora.9de0fa81a5a4.css", "_css/novo-alteracao.css": "_css/novo-alteracao.6aa533433d9b.css", "_css/estilo.css": "_css/estilo.19f3890ba152.css", "_css/crud.css": "_css/crud.892b286c0e80.css", "_css/produto_pesquisa.css": "_css/produto_pesquisa.90d5a5e73c8d.css", "css/bootstrap.min.css": "css/bootstrap.min.5a301aebe1ee.css", "css/bootstrap.min.css.map": "css/bootstrap.min.css.76b91c480140.map"}, "version": "1.0"}